test_chekc1/__init__.py
test_chekc1/core.py
test_chekc1-0.1.1.dist-info/METADATA
test_chekc1-0.1.1.dist-info/WHEEL
test_chekc1-0.1.1.dist-info/top_level.txt
test_chekc1-0.1.1.dist-info/RECORD
